pydocq/__init__.py
pydocq/cli.py
pydocq/analyzer/__init__.py
pydocq/analyzer/ast_analyzer.py
pydocq/analyzer/discovery.py
pydocq/analyzer/errors.py
pydocq/analyzer/formatter.py
pydocq/analyzer/inspector.py
pydocq/analyzer/output_formats.py
pydocq/analyzer/resolver.py
pydocq/analyzer/search.py
pydocq/analyzer/type_parser.py
pydocq/commands/__init__.py
pydocq/formatter/__init__.py
pydocq/sdk/__init__.py
pydocq/sdk/decorators.py
pydocq/utils/__init__.py
pydocq/utils/type_detection.py
pydocq-0.2.0.dist-info/METADATA
pydocq-0.2.0.dist-info/WHEEL
pydocq-0.2.0.dist-info/entry_points.txt
pydocq-0.2.0.dist-info/licenses/LICENSE
pydocq-0.2.0.dist-info/RECORD
