Metadata-Version: 2.4
Name: pydocq
Version: 0.2.0
Summary: Query Python package documentation for AI agents
Project-URL: Homepage, https://github.com/yourusername/pydocq
Project-URL: Documentation, https://github.com/yourusername/pydocq#readme
Project-URL: Repository, https://github.com/yourusername/pydocq.git
Project-URL: Issues, https://github.com/yourusername/pydocq/issues
Author: pydocq contributors
License: MIT
License-File: LICENSE
Keywords: agent,ai,ast,cli,documentation,introspection,metadata,python,sdk
Classifier: Development Status :: 4 - Beta
Classifier: Intended Audience :: Developers
Classifier: License :: OSI Approved :: MIT License
Classifier: Programming Language :: Python :: 3
Classifier: Programming Language :: Python :: 3.10
Classifier: Programming Language :: Python :: 3.11
Classifier: Programming Language :: Python :: 3.12
Classifier: Programming Language :: Python :: 3.13
Classifier: Programming Language :: Python :: 3.14
Classifier: Topic :: Software Development :: Documentation
Classifier: Topic :: Software Development :: Libraries :: Python Modules
Classifier: Topic :: Utilities
Requires-Python: >=3.10
Requires-Dist: typer>=0.12.0
Provides-Extra: dev
Requires-Dist: black>=24.0.0; extra == 'dev'
Requires-Dist: pytest-cov>=4.1.0; extra == 'dev'
Requires-Dist: pytest>=8.0.0; extra == 'dev'
Requires-Dist: ruff>=0.1.0; extra == 'dev'
